py_utlx-2.1.2.dist-info/licenses/LICENSE
utlx/__about__.py
utlx/__init__.py
utlx/_adict.py
utlx/_borg.py
utlx/_cache.py
utlx/_classproperty.py
utlx/_const.py
utlx/_defined.py
utlx/_deprecated.py
utlx/_dllpath.py
utlx/_ftee.py
utlx/_modpath.py
utlx/_public.py
utlx/_renumerate.py
utlx/_run.py
utlx/_rwproperty.py
utlx/_rwproperty.txt
utlx/_rwproperty_utlx.txt
utlx/_unique.py
utlx/_util.py
utlx/config.py
utlx/epath.py
utlx/imports.py
utlx/py.typed
utlx/ctypes/__init__.py
utlx/ctypes/_c_ptr.py
utlx/platform/__init__.py
utlx/platform/_detect.py
utlx/platform/_limits.py
utlx/platform/_oid.py
utlx/platform/capi.py
utlx/platform/linux/__init__.py
utlx/platform/linux/_arch.py
utlx/platform/linux/capi.py
utlx/platform/macos/__init__.py
utlx/platform/macos/_arch.py
utlx/platform/macos/capi.py
utlx/platform/windows/__init__.py
utlx/platform/windows/_arch.py
utlx/platform/windows/capi.py
utlx/platform/windows/winapi.py
py_utlx-2.1.2.dist-info/METADATA
py_utlx-2.1.2.dist-info/WHEEL
py_utlx-2.1.2.dist-info/top_level.txt
py_utlx-2.1.2.dist-info/zip-safe
py_utlx-2.1.2.dist-info/RECORD
